[
	{
		"title": "Network Graph (Silos and Isolates)",
		"url": "https://physicalpixel.github.io/D3/Network_Graph/index.html",
		"name": "Silos and Isolates",
		"tech": ["Projects", "D3.js", "css", "html"],
		"tags": ["force simulation", "dataviz", "visualization", "network graph", "d3.js", "css", "html", "js", "interactive"],
		"data": {},
		"color": "#EEEEEE"
	},
	{
		"title": "Interactive Timeseries",
		"url": "https://physicalpixel.github.io/TimeSeries/index.html",
		"name": "TimeSeries Bar Chart",
		"tech": ["Projects", "D3.js", "css", "html"],
		"tags": ["dataviz", "visualization", "d3.js", "css", "html", "js", "radial", "bar chart", "brush", "racing", "interactive", "timeseries", "slider"],
		"data": {},
		"color": "#EEEEEE"
	},
	{
		"title": "Organizational Network Simulator",
		"url": "https://physicalpixel.github.io/Network_Simulator/Network_Simulator/index.htm",
		"name": "Interactive Network Graph",
		"tech": ["Projects", "Cytoscape.js", "css", "html", "Bootstrap"],
		"tags": ["bootstrap", "dataviz", "visualization", "cytoscape.js", "css", "html", "js", "radial", "bar chart", "brush", "racing", "interactive", "timeseries", "slider"],
		"data": {},
		"color": "#EEEEEE"
	},
	{
		"title": "Extreme tempratures over the years",
		"url": "https://physicalpixel.github.io/D3/Extreme_Temperature/index.html",
		"name": "Interactive Map Viz",
		"tech": ["Projects", "D3.js", "css", "html"],
		"tags": ["geojson", "dataviz", "visualization", "d3.js", "css", "html", "js", "mercator", "geographic", "timeseries", "interactive", "slider"],
		"data": {},
		"color": "#EEEEEE"
	},
	{
		"title": "Stock Market Trend",
		"url": "https://physicalpixel.github.io/Assessments/Assessment_2/index.html",
		"name": "Intearctive Line chart",
		"tech": ["Projects", "D3.js", "css", "html"],
		"tags": ["line chart", "dataviz", "visualization", "d3.js", "stock market", "css", "html", "js", "interactive", "slider"],
		"data": {},
		"color": "#EEEEEE"
	},
	{
		"title": "Image Mapper",
		"url": "https://physicalpixel.github.io/Assessments/Assessment_1/index.html",
		"name": "Intearctive Line chart",
		"tech": ["Projects", "js", "css", "html"],
		"tags": ["application", "image mapper", "css", "html", "js", "interactive"],
		"data": {},
		"color": "#EEEEEE"
	},
	{
		"title": "Top Emitting Companies",
		"url": "https://physicalpixel.github.io/D3/Final_Draft.html",
		"name": "Custom Radial Scatter Plot",
		"tech": ["Projects", "D3.js", "css", "html"],
		"tags": ["dataviz", "visualization", "d3.js", "css", "html", "js", "radial", "scatter plot"],
		"data": {},
		"color": "#EEEEEE"
	},
	{
		"title": "Climate Risk Index",
		"url": "https://physicalpixel.github.io/D3/CRI.html",
		"name": "Custom Radial Bar Chart ",
		"tech": ["Projects", "D3.js", "css", "html"],
		"tags": ["dataviz", "visualization", "d3.js", "css", "html", "js", "radial", "bar chart"],
		"data": {},
		"color": "#EEEEEE"
	},
	{
		"title": "California Wildfire",
		"url": "https://physicalpixel.github.io/D3/california2.gif",
		"name": "Custom Map Viz with Kepler.gl(Gif)",
		"tech": ["Projects", "Design", "kepler.gl", "Photoshop"],
		"tags": ["dataviz", "visualization", "scatter plot", "mercator", "geographic", "timeseries"],
		"data": {},
		"color": "#EEEEEE"
	},
	{
		"title": "Sample Landing Pages",
		"url": "https://github.com/Physicalpixel/Landing_Page",
		"name": "Moving background Landing Page",
		"tech": ["Projects", "Design", "D3.js", "css", "js", "html"],
		"tags": ["3d", "ui", "landing page", "web", "single page", "layout", "sample", "dataviz", "visualization", "scatter plot", "mercator", "geographic", "timeseries"],
		"data": {},
		"color": "#EEEEEE"
	},
	{
		"title": "Organization Network Graphs",
		"url": "https://github.com/Physicalpixel/OG_Graph_Cytoscape",
		"name": "Cytoscape.js Network Graphs",
		"tech": ["Projects", "Cytoscape.js", "css", "js", "html", "cytoscape.js"],
		"tags": ["cytoscape.js", "network graph", "organizational", "3d", "ui", "landing page", "web", "single page", "layout", "sample", "dataviz", "visualization", "scatter plot", "mercator", "geographic", "timeseries"],
		"data": {},
		"color": "#EEEEEE"
	},
	{
		"title": "Graphic and UI",
		"url": "https://www.behance.net/preethi91",
		"name": "Graphic Design and UI",
		"tech": ["Projects", "Design"],
		"tags": ["design"],
		"data": {},
		"color": "#EEEEEE"
	},
	{
		"title": "New Media Art",
		"url": "https://preethikaran91.wixsite.com/portfolio",
		"name": "Experimental Media",
		"tech": ["Projects", "Design", "New-Media"],
		"tags": ["design", "new media", "arts", "art"],
		"data": {},
		"color": "#EEEEEE"
	}
]
